odoo8_addon_portal_payment_mode-8.0.1.0.0-py2.7-nspkg.pth
odoo_addons/portal_payment_mode/__openerp__.py
odoo_addons/portal_payment_mode/__init__.py
odoo_addons/portal_payment_mode/README.rst
odoo_addons/portal_payment_mode/security/ir.model.access.csv
odoo_addons/portal_payment_mode/tests/__init__.py
odoo_addons/portal_payment_mode/tests/test_portal_payment_mode.py
odoo_addons/portal_payment_mode/static/description/icon.png
odoo8_addon_portal_payment_mode-8.0.1.0.0.dist-info/top_level.txt
odoo8_addon_portal_payment_mode-8.0.1.0.0.dist-info/WHEEL
odoo8_addon_portal_payment_mode-8.0.1.0.0.dist-info/RECORD
odoo8_addon_portal_payment_mode-8.0.1.0.0.dist-info/metadata.json
odoo8_addon_portal_payment_mode-8.0.1.0.0.dist-info/DESCRIPTION.rst
odoo8_addon_portal_payment_mode-8.0.1.0.0.dist-info/METADATA
odoo8_addon_portal_payment_mode-8.0.1.0.0.dist-info/namespace_packages.txt
